MLstatkit/__init__.py
MLstatkit/ci.py
MLstatkit/conversions.py
MLstatkit/delong.py
MLstatkit/metrics.py
MLstatkit/permutation.py
MLstatkit/stats.py
mlstatkit-0.1.91.dist-info/licenses/LICENSE
mlstatkit-0.1.91.dist-info/METADATA
mlstatkit-0.1.91.dist-info/WHEEL
mlstatkit-0.1.91.dist-info/top_level.txt
mlstatkit-0.1.91.dist-info/RECORD
