Metadata-Version: 2.4
Name: MLstatkit
Version: 0.1.91
Summary: MLstatkit integrates established statistical methods into ML workflows (DeLong test, bootstrapping CI, AUC2OR, permutation test, etc.).
Author-email: Yong-Zhen Huang <m946111005@tmu.edu.tw>
License: MIT
Project-URL: Homepage, https://github.com/Brritany/MLstatkit
Project-URL: Issues, https://github.com/Brritany/MLstatkit/issues
Project-URL: Documentation, https://github.com/Brritany/MLstatkit#readme
Keywords: python,statistics,DeLong test,bootstrapping,AUC2OR,machine learning,permutation test
Classifier: Development Status :: 5 - Production/Stable
Classifier: Intended Audience :: Science/Research
Classifier: License :: OSI Approved :: MIT License
Classifier: Natural Language :: English
Classifier: Programming Language :: Python :: 3
Classifier: Programming Language :: Python :: 3 :: Only
Classifier: Programming Language :: Python :: 3.8
Classifier: Programming Language :: Python :: 3.9
Classifier: Programming Language :: Python :: 3.10
Classifier: Programming Language :: Python :: 3.11
Classifier: Programming Language :: Python :: 3.12
Classifier: Topic :: Scientific/Engineering
Classifier: Topic :: Software Development :: Libraries :: Python Modules
Requires-Python: >=3.8
License-File: LICENSE
Requires-Dist: numpy>=1.20.0
Requires-Dist: scipy>=1.7.0
Requires-Dist: scikit-learn>=1.0.0
Requires-Dist: tqdm>=4.0.0
Provides-Extra: dev
Requires-Dist: pytest>=7.0; extra == "dev"
Requires-Dist: pytest-cov>=4.0; extra == "dev"
Requires-Dist: ruff>=0.5.0; extra == "dev"
Dynamic: license-file
